oeahr_package/__init__.py
oeahr_package/test_dyna.py
oeahr_package/test_dyna_2.py
oeahr_package/utils.py
oeahr_package-0.0.9.dist-info/METADATA
oeahr_package-0.0.9.dist-info/WHEEL
oeahr_package-0.0.9.dist-info/entry_points.txt
oeahr_package-0.0.9.dist-info/top_level.txt
oeahr_package-0.0.9.dist-info/RECORD
